{"cameraMode":{"drawMode":0,"name":"Shaded","section":"Shading Mode"},"sceneLighting":true,"audioPlay":false,"sceneViewState":{"m_AlwaysRefresh":false,"showFog":true,"showSkybox":true,"showFlares":true,"showImageEffects":true,"showParticleSystems":true,"showVisualEffectGraphs":true,"m_FxEnabled":true},"in2DMode":false,"pivot":{"x":520.69482421875,"y":788.4345703125,"z":225.20654296875},"rotation":{"x":0.10028572380542755,"y":0.5604565143585205,"z":-0.06860863417387009,"w":0.8192262053489685},"size":1168.5869140625,"orthographic":false}